{"nodes": [{"id": "0", "title": "0", "label": "Nodo 1", "shape": null, "size": 25, "color": null}, {"id": "1", "title": "1", "label": "Nodo 2", "shape": null, "size": 25, "color": null}, {"id": "2", "title": "2", "label": "Nodo 3", "shape": null, "size": 25, "color": null}, {"id": "3", "title": "3", "label": "Nodo 4", "shape": null, "size": 25, "color": null}, {"id": "4", "title": "4", "label": "Nodo 5", "shape": null, "size": 25, "color": "#ff0000"}, {"id": "5", "title": "5", "label": "Nodo 6", "shape": null, "size": 25, "color": null}], "edges": [{"source": "0", "from": "0", "to": "1", "color": "#F7A7A6", "label": "616", "width": 3, "directed": false}, {"source": "0", "from": "0", "to": "2", "color": "#F7A7A6", "label": "308", "width": 3, "directed": false}, {"source": "0", "from": "0", "to": "3", "color": "#F7A7A6", "label": "895", "width": 3, "directed": false}, {"source": "0", "from": "0", "to": "4", "color": "#F7A7A6", "label": "30", "width": 3, "directed": false}, {"source": "0", "from": "0", "to": "5", "color": "#F7A7A6", "label": "264", "width": 3, "directed": false}, {"source": "1", "from": "1", "to": "2", "color": "#F7A7A6", "label": "19", "width": 3, "directed": false}, {"source": "1", "from": "1", "to": "3", "color": "#F7A7A6", "label": "348", "width": 3, "directed": false}, {"source": "1", "from": "1", "to": "4", "color": "#F7A7A6", "label": "330", "width": 3, "directed": false}, {"source": "1", "from": "1", "to": "5", "color": "#F7A7A6", "label": "538", "width": 3, "directed": false}, {"source": "2", "from": "2", "to": "3", "color": "#F7A7A6", "label": "102", "width": 3, "directed": false}, {"source": "2", "from": "2", "to": "4", "color": "#F7A7A6", "label": "170", "width": 3, "directed": false}, {"source": "2", "from": "2", "to": "5", "color": "#F7A7A6", "label": "584", "width": 3, "directed": false}, {"source": "3", "from": "3", "to": "4", "color": "#F7A7A6", "label": "129", "width": 3, "directed": false}, {"source": "3", "from": "3", "to": "5", "color": "#F7A7A6", "label": "790", "width": 3, "directed": false}, {"source": "4", "from": "4", "to": "5", "color": "#F7A7A6", "label": "494", "width": 3, "directed": false}], "directed": true}